pydatamanager/__init__.py
pydatamanager/data.py
pydatamanager/h5modules/__init__.py
pydatamanager/h5modules/backends.py
pydatamanager/h5modules/browsing.py
pydatamanager/h5modules/data_saving.py
pydatamanager/h5modules/exporter.py
pydatamanager/h5modules/h5logging.py
pydatamanager/h5modules/module_saving.py
pydatamanager/h5modules/saving.py
pydatamanager/h5modules/utils.py
pydatamanager/h5modules/exporters/__init__.py
pydatamanager/h5modules/exporters/base.py
pydatamanager/h5modules/exporters/flimj.py
pydatamanager/h5modules/exporters/hyperspy.py
pydatamanager/plotting/__init__.py
pydatamanager/plotting/gant_chart.py
pydatamanager/plotting/image_viewer.py
pydatamanager/plotting/navigator.py
pydatamanager/plotting/scan_selector.py
pydatamanager/plotting/widgets.py
pydatamanager/plotting/data_viewers/__init__.py
pydatamanager/plotting/data_viewers/base.py
pydatamanager/plotting/data_viewers/viewer.py
pydatamanager/plotting/data_viewers/viewer0D.py
pydatamanager/plotting/data_viewers/viewer1D.py
pydatamanager/plotting/data_viewers/viewer1Dbasic.py
pydatamanager/plotting/data_viewers/viewer2D.py
pydatamanager/plotting/data_viewers/viewer2D_basic.py
pydatamanager/plotting/data_viewers/viewerND.py
pydatamanager/plotting/items/__init__.py
pydatamanager/plotting/items/axis_scaled.py
pydatamanager/plotting/items/crosshair.py
pydatamanager/plotting/items/image.py
pydatamanager/plotting/plotter/plotter.py
pydatamanager/plotting/plotter/plotters/__init__.py
pydatamanager/plotting/plotter/plotters/matplotlib_plotters.py
pydatamanager/plotting/plotter/plotters/qt_plotters.py
pydatamanager/plotting/utils/__init__.py
pydatamanager/plotting/utils/axes_viewer.py
pydatamanager/plotting/utils/filter.py
pydatamanager/plotting/utils/lineout.py
pydatamanager/plotting/utils/plot_utils.py
pydatamanager/plotting/utils/signalND.py
pydatamanager/resources/VERSION
pydatamanager-0.0.1a2.dist-info/METADATA
pydatamanager-0.0.1a2.dist-info/WHEEL
pydatamanager-0.0.1a2.dist-info/licenses/LICENSE
pydatamanager-0.0.1a2.dist-info/RECORD
