Metadata-Version: 2.3
Name: pydatamanager
Version: 0.0.1a2
Summary: Physical Data Management - Manipulation - Mathematical operations - Saving - Plotting
Project-URL: Homepage, http://pymodaq.cnrs.fr
Project-URL: Source, https://github.com/PyMoDAQ/pydata
Project-URL: Tracker, https://github.com/PyMoDAQ/pydata/issues
Author-email: Sébastien Weber <sebastien.weber@cemes.fr>
License: The MIT License (MIT)
License-File: LICENSE
Classifier: Development Status :: 5 - Production/Stable
Classifier: Environment :: Other Environment
Classifier: Intended Audience :: Science/Research
Classifier: License :: OSI Approved :: MIT License
Classifier: Natural Language :: English
Classifier: Operating System :: OS Independent
Classifier: Programming Language :: Python :: 3.7
Classifier: Programming Language :: Python :: 3.8
Classifier: Programming Language :: Python :: 3.9
Classifier: Programming Language :: Python :: 3.10
Classifier: Programming Language :: Python :: 3.11
Classifier: Topic :: Scientific/Engineering :: Human Machine Interfaces
Classifier: Topic :: Scientific/Engineering :: Visualization
Classifier: Topic :: Software Development :: Libraries :: Python Modules
Classifier: Topic :: Software Development :: User Interfaces
Requires-Python: >=3.7
Requires-Dist: multipledispatch
Requires-Dist: numpy<2.0.0
Requires-Dist: packaging
Requires-Dist: pint
Requires-Dist: scipy
Requires-Dist: setuptools>=60
Requires-Dist: tables<3.9
Requires-Dist: toml
